mcp_video_download_url_parser/__init__.py
mcp_video_download_url_parser/__main__.py
mcp_video_download_url_parser/server.py
mcp_video_download_url_parser-0.1.0.dist-info/METADATA
mcp_video_download_url_parser-0.1.0.dist-info/WHEEL
mcp_video_download_url_parser-0.1.0.dist-info/entry_points.txt
mcp_video_download_url_parser-0.1.0.dist-info/licenses/LICENSE
mcp_video_download_url_parser-0.1.0.dist-info/RECORD
