Metadata-Version: 2.4
Name: mcp-video-download-url-parser
Version: 0.1.0
Summary: 从抖音、TikTok等平台下载无水印视频的MCP服务
Project-URL: Homepage, https://github.com/tansunyj/mcp_video_download_url_parser
Author: tansunyj
License: MIT
License-File: LICENSE
Classifier: Development Status :: 3 - Alpha
Classifier: Intended Audience :: Developers
Classifier: Operating System :: OS Independent
Classifier: Programming Language :: Python :: 3.10
Classifier: Programming Language :: Python :: 3.11
Classifier: Programming Language :: Python :: 3.12
Classifier: Topic :: Software Development :: Libraries :: Python Modules
Requires-Python: >=3.10
Requires-Dist: aiofiles>=23.1.0
Requires-Dist: asyncio>=3.4.3
Requires-Dist: beautifulsoup4>=4.9.3
Requires-Dist: build>=1.2.2.post1
Requires-Dist: fastmcp>=1.0.0
Requires-Dist: httpx>=0.24.0
Requires-Dist: playwright>=1.40.0
Requires-Dist: requests>=2.26.0
Requires-Dist: twine>=6.1.0
